discat/__init__.py
discat-2023.8.13.1.dist-info/METADATA
discat-2023.8.13.1.dist-info/WHEEL
discat-2023.8.13.1.dist-info/top_level.txt
discat-2023.8.13.1.dist-info/RECORD
